mopa/__init__.py
mopa/analysis.py
mopa/analysis_testing.py
mopa/app.py
mopa/viz.py
mopa-2.2.2b0.dist-info/LICENSE
mopa-2.2.2b0.dist-info/METADATA
mopa-2.2.2b0.dist-info/WHEEL
mopa-2.2.2b0.dist-info/top_level.txt
mopa-2.2.2b0.dist-info/RECORD
