Metadata-Version: 2.1
Name: mopa
Version: 2.2.2b0
Summary: Library for interactive multi-objective power amplifier design
Home-page: https://github.com/kravitsjacob/mopa
Author: Jacob Kravits
Author-email: kravitsjacob@gmail.com
License: UNKNOWN
Project-URL: Bug Tracker, https://github.com/kravitsjacob/mopa/issues
Platform: UNKNOWN
Classifier: Programming Language :: Python :: 3
Classifier: License :: OSI Approved :: MIT License
Classifier: Operating System :: OS Independent
Requires-Python: >=3.9
License-File: LICENSE
Requires-Dist: pandas
Requires-Dist: hiplot
Requires-Dist: dash
Requires-Dist: dash-bootstrap-components
